setup.py
Downpy.egg-info/PKG-INFO
Downpy.egg-info/SOURCES.txt
Downpy.egg-info/dependency_links.txt
Downpy.egg-info/entry_points.txt
Downpy.egg-info/not-zip-safe
Downpy.egg-info/top_level.txt
downpy/__init__.py
downpy/cmdline.py
downpy/downloader.py
downpy/extensions.py
downpy/parser.py
downpy/urlqueue.py
downpy/beautifulsoup/BeautifulSoup.py
downpy/beautifulsoup/__init__.py
downpy/ui/__init__.py
downpy/ui/progressbar.py