Metadata-Version: 1.0
Name: Downpy
Version: 1.2
Summary: Downpy is a command line tool that downloads all files of a certain media type in a webpage.
Home-page: http://github.com/rogeriopvl/Downpy
Author: Rogerio Vicente
Author-email: rogeriopvl@gmail.com
License: BSD License
Keywords: download files
Platform: any
Classifier: License :: OSI Approved :: BSD License
Classifier: Intended Audience :: Developers
Classifier: Intended Audience :: End Users/Desktop
Classifier: Development Status :: 4 - Beta
Classifier: Programming Language :: Python :: 2
Classifier: Programming Language :: Python :: 3
Classifier: Operating System :: OS Independent
